fmkr/__init__.py
fmkr/fmkr.py
fmkr/py.typed
fmkr-2026.1.6.dist-info/licenses/LICENSE
fmkr-2026.1.6.dist-info/METADATA
fmkr-2026.1.6.dist-info/WHEEL
fmkr-2026.1.6.dist-info/top_level.txt
fmkr-2026.1.6.dist-info/RECORD
