Metadata-Version: 2.4
Name: fmkr
Version: 2026.1.6
Summary: Access FileMaker(tm) Server Databases
Home-page: https://www.cgohlke.com
Author: Christoph Gohlke
Author-email: cgohlke@cgohlke.com
License: BSD-3-Clause
Project-URL: Bug Tracker, https://github.com/cgohlke/fmkr/issues
Project-URL: Source Code, https://github.com/cgohlke/fmkr
Platform: any
Classifier: Development Status :: 4 - Beta
Classifier: Topic :: Database
Classifier: Intended Audience :: Developers
Classifier: Operating System :: OS Independent
Classifier: Programming Language :: Python :: 3 :: Only
Classifier: Programming Language :: Python :: 3.11
Classifier: Programming Language :: Python :: 3.12
Classifier: Programming Language :: Python :: 3.13
Classifier: Programming Language :: Python :: 3.14
Requires-Python: >=3.11
License-File: LICENSE
Requires-Dist: lxml
Dynamic: author
Dynamic: author-email
Dynamic: classifier
Dynamic: description
Dynamic: description-content-type
Dynamic: home-page
Dynamic: license
Dynamic: license-file
Dynamic: platform
Dynamic: project-url
Dynamic: requires-dist
Dynamic: requires-python
Dynamic: summary
